streamfig/__init__.py
streamfig/streamfig.py
streamfig-1.2.dist-info/LICENSE
streamfig-1.2.dist-info/LICENSE.txt
streamfig-1.2.dist-info/METADATA
streamfig-1.2.dist-info/WHEEL
streamfig-1.2.dist-info/top_level.txt
streamfig-1.2.dist-info/RECORD
