Metadata-Version: 2.1
Name: streamfig
Version: 1.2
Summary: Draw stream graphs into FIG format
Home-page: https://github.com/TiphaineV/streamfig
Author: Tiphaine Viard
Author-email: tiphaine.viard@telecom-paris.fr
License: UNKNOWN
Download-URL: https://github.com/TiphaineV/streamfig/archive/1.2.tar.gz
Keywords: stream graphs,visualization,temporal networks,xfig
Platform: UNKNOWN
